pytest_srcpaths.py
pytest_srcpaths-1.2.1.dist-info/entry_points.txt
pytest_srcpaths-1.2.1.dist-info/LICENSE
pytest_srcpaths-1.2.1.dist-info/WHEEL
pytest_srcpaths-1.2.1.dist-info/METADATA
pytest_srcpaths-1.2.1.dist-info/RECORD
