Metadata-Version: 2.1
Name: pytest-srcpaths
Version: 1.2.1
Summary: Add paths to sys.path
Author-email: Brian Okken <brian+pypi@pythontest.com>
Requires-Python: >=3.7
Classifier: License :: OSI Approved :: MIT License
Requires-Dist: pytest>=6.2.0
Requires-Dist: tox ; extra == "test"
Project-URL: Home, https://github.com/okken/pytest-srcpaths
Provides-Extra: test
